panduza_server/__init__.py
panduza_server/manage.py
panduza_server/panduza/__init__.py
panduza_server/panduza/asgi.py
panduza_server/panduza/plugins.py
panduza_server/panduza/settings.py
panduza_server/panduza/urls.py
panduza_server/panduza/views.py
panduza_server/panduza/wsgi.py
panduza_server/panduza/interfaces/__init__.py
panduza_server/panduza/interfaces/io.py
panduza_server/scripts/__init__.py
panduza_server/scripts/server.py
panduza_server/static/css/index.css
panduza_server/static/css/io_card.css
panduza_server/static/css/io_control.css
panduza_server/static/img/panduza_logo.png
panduza_server/static/js/CardIoControl.js
panduza_server/static/js/PluginStatus.js
panduza_server/static/js/axios.min.js
panduza_server/static/js/babel.min.js
panduza_server/static/js/material-ui.production.min.js
panduza_server/static/js/react-dom.production.min.js
panduza_server/static/js/react.production.min.js
panduza_server/templates/index.html
panduza_server/templates/io_multi_control.html
panduza_server/templates/io_single_control.html
panduza_server/templates/plugins.html
panduza_server-0.0.1.dist-info/METADATA
panduza_server-0.0.1.dist-info/WHEEL
panduza_server-0.0.1.dist-info/entry_points.txt
panduza_server-0.0.1.dist-info/top_level.txt
panduza_server-0.0.1.dist-info/RECORD
